pandas_schema/__init__.py
pandas_schema/column.py
pandas_schema/errors.py
pandas_schema/schema.py
pandas_schema/validation.py
pandas_schema/validation_warning.py
pandas_schema/version.py
pandas_schema-0.3.6.dist-info/LICENSE
pandas_schema-0.3.6.dist-info/METADATA
pandas_schema-0.3.6.dist-info/WHEEL
pandas_schema-0.3.6.dist-info/top_level.txt
pandas_schema-0.3.6.dist-info/RECORD
