Metadata-Version: 2.1
Name: pandas-schema
Version: 0.3.6
Summary: A validation library for Pandas data frames using user-friendly schemas
Home-page: https://github.com/TMiguelT/PandasSchema
Author: Michael Milton
Author-email: michael.r.milton@gmail.com
License: MIT
Keywords: pandas csv verification schema
Platform: UNKNOWN
Classifier: Development Status :: 5 - Production/Stable
Classifier: Intended Audience :: Developers
Classifier: License :: OSI Approved :: MIT License
Classifier: Programming Language :: Python :: 3 :: Only
Classifier: Programming Language :: Python :: 3.5
License-File: LICENSE
